cryptlex/__init__.py
cryptlex/lexfloatclient/__init__.py
cryptlex/lexfloatclient/lexfloatclient.py
cryptlex/lexfloatclient/lexfloatclient_exception.py
cryptlex/lexfloatclient/lexfloatclient_native.py
cryptlex/lexfloatclient/lexfloatstatus_codes.py
cryptlex/lexfloatclient/libs/linux/gcc/arm64/libLexFloatClient.so
cryptlex/lexfloatclient/libs/linux/gcc/x86/libLexFloatClient.so
cryptlex/lexfloatclient/libs/linux/gcc/x86_64/libLexFloatClient.so
cryptlex/lexfloatclient/libs/linux/musl/x86_64/libLexFloatClient.so
cryptlex/lexfloatclient/libs/macos/arm64/libLexFloatClient.dylib
cryptlex/lexfloatclient/libs/macos/x86_64/libLexFloatClient.dylib
cryptlex/lexfloatclient/libs/win32/arm64/LexFloatClient.dll
cryptlex/lexfloatclient/libs/win32/x86/LexFloatClient.dll
cryptlex/lexfloatclient/libs/win32/x86_64/LexFloatClient.dll
cryptlex_lexfloatclient-4.13.0.dist-info/licenses/LICENSE.txt
cryptlex_lexfloatclient-4.13.0.dist-info/METADATA
cryptlex_lexfloatclient-4.13.0.dist-info/WHEEL
cryptlex_lexfloatclient-4.13.0.dist-info/top_level.txt
cryptlex_lexfloatclient-4.13.0.dist-info/RECORD
